[
    {
        "name": "CRIMINALDISTRICTCOURT",
        "speech": [
            {
                "content": " Officer Peter Paul.",
                "index": 1337,
                "length": 20
            },
            {
                "content": " Police officer.",
                "index": 1395,
                "length": 16
            },
            {
                "content": " Yes, right there at the desk in the orange jumpsuit.",
                "index": 1453,
                "length": 53
            },
            {
                "content": " In undercover plain clothes capacity with Eighth District Narcotics.",
                "index": 1693,
                "length": 69
            },
            {
                "content": " Yes.",
                "index": 1887,
                "length": 5
            }
        ]
    },
    {
        "name": "STATEOFLOUISIANA",
        "speech": [
            {
                "content": "S- Crime Lab\n",
                "index": 747,
                "length": 13
            },
            {
                "content": "S- Conviction\n",
                "index": 760,
                "length": 14
            }
        ]
    },
    {
        "name": "NO",
        "speech": [
            {
                "content": " 123-456\n",
                "index": 84,
                "length": 9
            }
        ]
    },
    {
        "name": "JOHNDOE",
        "speech": [
            {
                "content": "Probable Cause Hearing\n",
                "index": 122,
                "length": 23
            },
            {
                "content": "Motion to Suppress Evidence\n",
                "index": 145,
                "length": 28
            },
            {
                "content": "Testimony and Notes of Evidence, taken in the above-entitled and -numbered cause, before the HON.",
                "index": 173,
                "length": 97
            },
            {
                "content": " JOHN JUSTICE, Judge, presiding on the 7th day of May, 2014.",
                "index": 270,
                "length": 60
            }
        ]
    },
    {
        "name": "JANESMITHESQ",
        "speech": [
            {
                "content": "Your Honor, the State is ready to proceed with motions in John Doe.",
                "index": 786,
                "length": 67
            },
            {
                "content": "Your Honor, Mary Jane on behalf of John Doe.",
                "index": 865,
                "length": 44
            },
            {
                "content": "Yes.",
                "index": 982,
                "length": 4
            },
            {
                "content": " Mr.",
                "index": 986,
                "length": 4
            },
            {
                "content": " Doe is present in court and we're ready for motions.",
                "index": 990,
                "length": 53
            },
            {
                "content": "The State calls Officer Peter Paul.",
                "index": 1104,
                "length": 35
            },
            {
                "content": "OFFICER PETER PAUL, Parish Police Department, after having been first duly sworn, did testify as follows:\n",
                "index": 1141,
                "length": 106
            },
            {
                "content": " Could you please state your name for the Record?",
                "index": 1285,
                "length": 49
            },
            {
                "content": " Officer, how are you employed?",
                "index": 1361,
                "length": 31
            },
            {
                "content": " Do you see Mr.",
                "index": 1415,
                "length": 15
            },
            {
                "content": " Doe in court today?",
                "index": 1430,
                "length": 20
            },
            {
                "content": "Please let the Record reflect proper in-court identification.",
                "index": 1519,
                "length": 61
            },
            {
                "content": " Officer, could you tell the Court in what capacity you were working February, ?",
                "index": 1610,
                "length": 80
            },
            {
                "content": "I tender the witness, Judge.",
                "index": 1775,
                "length": 28
            },
            {
                "content": " Officer, you were undercover on February, ?",
                "index": 1840,
                "length": 44
            },
            {
                "content": " Would it refresh your recollection if you looked at your police report?",
                "index": 1896,
                "length": 72
            },
            {
                "content": "Your Honor, I'm going to object.",
                "index": 1981,
                "length": 32
            },
            {
                "content": " I don't think it's relevant who did the physical detention of the defendant.",
                "index": 2013,
                "length": 77
            },
            {
                "content": "I have no further questions.",
                "index": 2392,
                "length": 28
            },
            {
                "content": " Thank you.",
                "index": 2420,
                "length": 11
            },
            {
                "content": "The State has no Redirect.",
                "index": 2444,
                "length": 26
            },
            {
                "content": "The State has no further witnesses.",
                "index": 2534,
                "length": 35
            },
            {
                "content": " Judge, at this time we would offer, file and introduce S- -- for motion purposes only -- S-, which is a copy of the crime lab in this matter showing that the evidence confiscated from the defendant, both the hand-rolled cigar and the nine plastic baggies were each positive for marijuana; and S-, a copy of the defendant's prior conviction.",
                "index": 2569,
                "length": 341
            },
            {
                "content": "Not for motion purposes.",
                "index": 2969,
                "length": 24
            },
            {
                "content": "With that, Judge, the State submits.",
                "index": 3006,
                "length": 36
            },
            {
                "content": "No.",
                "index": 3091,
                "length": 3
            },
            {
                "content": "I would submit.",
                "index": 3129,
                "length": 15
            },
            {
                "content": "The State submits.",
                "index": 3157,
                "length": 18
            }
        ]
    },
    {
        "name": "JOEREPORTERCCRRPR",
        "speech": [
            {
                "content": "Certified Court Reporter\n",
                "index": 4160,
                "length": 25
            },
            {
                "content": "Registered Professional Reporter\n",
                "index": 4185,
                "length": 33
            },
            {
                "content": "Certified Court Reporter\n",
                "index": 5142,
                "length": 25
            },
            {
                "content": "Registered Professional Reporter",
                "index": 5167,
                "length": 32
            }
        ]
    },
    {
        "name": "DETECTIVEPETERPAUL",
        "speech": [
            {
                "content": "Direct Examination by Ms.",
                "index": 662,
                "length": 25
            },
            {
                "content": " Smith\n",
                "index": 687,
                "length": 7
            },
            {
                "content": "Cross-Examination by Ms.",
                "index": 694,
                "length": 24
            },
            {
                "content": " Jane\n",
                "index": 718,
                "length": 6
            }
        ]
    },
    {
        "name": "THECOURT",
        "speech": [
            {
                "content": "This is the matter of the State versus John Doe.",
                "index": 922,
                "length": 48
            },
            {
                "content": "Very well.",
                "index": 1056,
                "length": 10
            },
            {
                "content": " Call your first witness.",
                "index": 1066,
                "length": 25
            },
            {
                "content": "I will permit it.",
                "index": 2103,
                "length": 17
            },
            {
                "content": " I will overrule.",
                "index": 2120,
                "length": 17
            },
            {
                "content": " Would it refresh your recollection, Officer, if you reviewed the police report?",
                "index": 2137,
                "length": 80
            },
            {
                "content": "Thank you, Officer.",
                "index": 2483,
                "length": 19
            },
            {
                "content": " You may step down.",
                "index": 2502,
                "length": 19
            },
            {
                "content": "Any objection for motion purposes?",
                "index": 2923,
                "length": 34
            },
            {
                "content": "Anything by the Defense?",
                "index": 3055,
                "length": 24
            },
            {
                "content": "Submitted?",
                "index": 3107,
                "length": 10
            },
            {
                "content": "The Court finds probable cause as charged.",
                "index": 3188,
                "length": 42
            },
            {
                "content": " The Court denies the Motion to Suppress Evidence.",
                "index": 3230,
                "length": 50
            },
            {
                "content": " I will note an objection on behalf of the Defense to the Court's ruling.",
                "index": 3280,
                "length": 73
            }
        ]
    },
    {
        "name": "THEWITNESS",
        "speech": [
            {
                "content": "Sure, I will take a look.",
                "index": 2232,
                "length": 25
            },
            {
                "content": " Yes.",
                "index": 2257,
                "length": 5
            },
            {
                "content": " In the report it says that I notified him he was under arrest, and read him his rights per Miranda, and arrested him.",
                "index": 2262,
                "length": 118
            }
        ]
    },
    {
        "name": "REPORTERSPAGE",
        "speech": [
            {
                "content": "I, JOE REPORTER, Certified Court Reporter in and for the State of Louisiana, the officer, as defined in Rule of the Federal Rules of Civil Procedure and/or Article (B)",
                "index": 3372,
                "length": 167
            },
            {
                "content": " of the Louisiana Code of Civil Procedure, before whom this proceeding was taken, do hereby state on the Record:\n",
                "index": 3539,
                "length": 113
            },
            {
                "content": "That due to the interaction in the spontaneous discourse of this proceeding, dashes (--)",
                "index": 3653,
                "length": 88
            },
            {
                "content": " have been used to indicate pauses, changes in thought, and/or talkovers; that same is the proper method for a Court Reporter's transcription of proceeding, and that the dashes (--)",
                "index": 3741,
                "length": 181
            },
            {
                "content": " do not indicate that words or phrases have been left out of this transcript;\n",
                "index": 3922,
                "length": 78
            },
            {
                "content": "That any words and/or names which could not be verified through reference material have been denoted with the phrase \"(spelled phonetically)",
                "index": 4001,
                "length": 140
            }
        ]
    },
    {
        "name": "REPORTERSCERTIFICATE",
        "speech": [
            {
                "content": "This certification is valid only for a transcript accompanied by my original signature and original required seal on this page.",
                "index": 4243,
                "length": 127
            },
            {
                "content": "I, JOE REPORTER, Official Court Reporter in and for the State of Louisiana, employed as an Official Court Reporter by Criminal District Court, Parish of Orleans for the State of Louisiana, do hereby certify that this testimony was reported by me in the stenotype reporting method, was prepared and transcribed by me or under my personal direction and supervision, and is a true and correct transcript to the best of my ability and understanding;\n",
                "index": 4372,
                "length": 446
            },
            {
                "content": "That the transcript has been prepared in compliance with the transcript format guidelines required by statute, or by rules of the board, or by the Supreme Court of Louisiana;\n",
                "index": 4819,
                "length": 175
            },
            {
                "content": "That I am not of counsel, not related to counsel or the parties herein, nor am I otherwise interested in the outcome of this matter.",
                "index": 4995,
                "length": 132
            }
        ]
    }
]